project2md/__init__.py
project2md/cli.py
project2md/config.py
project2md/default_config.yml
project2md/explicit_config_generator.py
project2md/formatters/__init__.py
project2md/formatters/base.py
project2md/formatters/factory.py
project2md/formatters/json.py
project2md/formatters/json_formatter.py
project2md/formatters/markdown.py
project2md/formatters/markdown_formatter.py
project2md/formatters/yaml.py
project2md/formatters/yaml_formatter.py
project2md/git.py
project2md/messages.py
project2md/signature_processor.py
project2md/stats.py
project2md/walker.py
project2md-1.3.2.dist-info/LICENSE
project2md-1.3.2.dist-info/METADATA
project2md-1.3.2.dist-info/WHEEL
project2md-1.3.2.dist-info/entry_points.txt
project2md-1.3.2.dist-info/RECORD
