Metadata-Version: 2.3
Name: project2md
Version: 1.3.2
Summary: Transform directories or git repositories into comprehensive Markdown documentation with intelligent file filtering and structure preservation.
Author: itsatony
Author-email: i@itsatony.com
Requires-Python: >=3.10
Classifier: Programming Language :: Python :: 3
Classifier: Programming Language :: Python :: 3.10
Classifier: Programming Language :: Python :: 3.11
Classifier: Programming Language :: Python :: 3.12
Classifier: Programming Language :: Python :: 3.13
Requires-Dist: chardet (>=3.0.4)
Requires-Dist: click (>=7.0.0)
Requires-Dist: gitpython (>=3.1.0)
Requires-Dist: humanize (>=3.0.0)
Requires-Dist: pathspec (>=0.9.0)
Requires-Dist: pyyaml (>=5.1.0)
Requires-Dist: rich (>=9.0.0)
Requires-Dist: setuptools (>=42.0.0)
Requires-Dist: toml (>=0.10.2)
